{
	"info": {
		"_postman_id": "3f40f5e3-2f50-436b-9c33-d791d9d3f5dd",
		"name": "Labenusers",
		"schema": "https://schema.getpostman.com/json/collection/v2.1.0/collection.json"
	},
	"item": [
		{
			"name": "getAllUsers",
			"protocolProfileBehavior": {
				"disableBodyPruning": true
			},
			"request": {
				"method": "GET",
				"header": [
					{
						"key": "Authorization",
						"value": "Nayara-dos-Santos-Brito-Carver",
						"type": "text"
					}
				],
				"body": {
					"mode": "raw",
					"raw": "",
					"options": {
						"raw": {
							"language": "json"
						}
					}
				},
				"url": {
					"raw": "https://us-central1-labenu-apis.cloudfunctions.net/labenusers/users\n",
					"protocol": "https",
					"host": [
						"us-central1-labenu-apis",
						"cloudfunctions",
						"net"
					],
					"path": [
						"labenusers",
						"users\n"
					]
				}
			},
			"response": []
		},
		{
			"name": "getUserByld",
			"request": {
				"method": "GET",
				"header": [
					{
						"key": "Authorization",
						"value": "Nayara-dos-Santos-Brito-Carver",
						"type": "text"
					}
				],
				"url": {
					"raw": "https://us-central1-labenu-apis.cloudfunctions.net/labenusers/users/:id\n",
					"protocol": "https",
					"host": [
						"us-central1-labenu-apis",
						"cloudfunctions",
						"net"
					],
					"path": [
						"labenusers",
						"users",
						":id\n"
					],
					"variable": [
						{
							"key": "id\n",
							"value": null
						}
					]
				}
			},
			"response": []
		},
		{
			"name": "searchUsers",
			"protocolProfileBehavior": {
				"disableBodyPruning": true
			},
			"request": {
				"method": "GET",
				"header": [
					{
						"key": "Authorization",
						"value": "Nayara-dos-Santos-Brito-Carver",
						"type": "text"
					}
				],
				"body": {
					"mode": "raw",
					"raw": "",
					"options": {
						"raw": {
							"language": "json"
						}
					}
				},
				"url": {
					"raw": "https://us-central1-labenu-apis.cloudfunctions.net/labenusers/users/search?name=&email=\n",
					"protocol": "https",
					"host": [
						"us-central1-labenu-apis",
						"cloudfunctions",
						"net"
					],
					"path": [
						"labenusers",
						"users",
						"search"
					],
					"query": [
						{
							"key": "name",
							"value": ""
						},
						{
							"key": "email",
							"value": "\n"
						}
					]
				}
			},
			"response": []
		},
		{
			"name": "criarUsuario",
			"request": {
				"method": "POST",
				"header": [
					{
						"key": "Authorization",
						"value": "Nayara-dos-Santos-Brito-Carver",
						"type": "text"
					}
				],
				"body": {
					"mode": "raw",
					"raw": "{\r\n    \"name\": \"Nayara dos Santos Brito\",\r\n    \"email\": \"nayaraSantos@gmail.com\"\r\n}",
					"options": {
						"raw": {
							"language": "json"
						}
					}
				},
				"url": {
					"raw": "https://us-central1-labenu-apis.cloudfunctions.net/labenusers/users\n",
					"protocol": "https",
					"host": [
						"us-central1-labenu-apis",
						"cloudfunctions",
						"net"
					],
					"path": [
						"labenusers",
						"users\n"
					]
				}
			},
			"response": []
		},
		{
			"name": "editUSus",
			"request": {
				"method": "PUT",
				"header": [
					{
						"key": "Authorization",
						"value": "Nayara-dos-Santos-Brito-Carver",
						"type": "text"
					}
				],
				"body": {
					"mode": "raw",
					"raw": "{\r\n    \"name\": \"Nayara dos Santos Brito\",\r\n    \"email\": \"nayaraSantos@gmail.com\"\r\n}\r\n",
					"options": {
						"raw": {
							"language": "json"
						}
					}
				},
				"url": {
					"raw": "https://us-central1-labenu-apis.cloudfunctions.net/labenusers/users/:id\n",
					"protocol": "https",
					"host": [
						"us-central1-labenu-apis",
						"cloudfunctions",
						"net"
					],
					"path": [
						"labenusers",
						"users",
						":id\n"
					],
					"variable": [
						{
							"key": "id\n",
							"value": null
						}
					]
				}
			},
			"response": []
		}
	]
}